gmsdb/__init__.py
gmsdb-3.0.dist-info/METADATA
gmsdb-3.0.dist-info/WHEEL
gmsdb-3.0.dist-info/top_level.txt
gmsdb-3.0.dist-info/RECORD
