Metadata-Version: 2.1
Name: gmsdb
Version: 3.0
Summary: GMSDB Clusterer
Home-page: https://github.com/berng/GMSDB
Author: Oleg I.Berngardt
Author-email: berng@rambler.ru
License: UNKNOWN
Keywords: clusterization
Platform: UNKNOWN
Classifier: Programming Language :: Python :: 3.11
Classifier: License :: OSI Approved :: MIT License
Classifier: Operating System :: OS Independent
Requires-Python: >=3.6
Requires-Dist: matplotlib
Requires-Dist: mlxtend
Requires-Dist: numpy
Requires-Dist: scikit-learn
Requires-Dist: scipy
Requires-Dist: statsmodels
